{"stats":{"minecraft:custom":{"minecraft:time_since_rest":43488,"minecraft:crouch_one_cm":178,"minecraft:damage_absorbed":320,"minecraft:play_time":43488,"minecraft:sprint_one_cm":132366,"minecraft:damage_taken":4994,"minecraft:walk_one_cm":108794,"minecraft:damage_blocked_by_shield":3740,"minecraft:sneak_time":126,"minecraft:aviate_one_cm":7008,"minecraft:jump":1822,"minecraft:damage_dealt":5848,"minecraft:leave_game":2,"minecraft:walk_on_water_one_cm":931,"minecraft:time_since_death":43488,"minecraft:total_world_time":43488,"minecraft:damage_dealt_absorbed":481,"minecraft:fall_one_cm":52547,"minecraft:fly_one_cm":598532},"minecraft:used":{"minecraft:netherite_sword":113,"minecraft:golden_apple":9,"minecraft:diamond_sword":72,"minecraft:bow":2,"minecraft:mace":10,"minecraft:wind_charge":56,"minecraft:netherite_chestplate":1,"minecraft:elytra":1,"minecraft:netherite_axe":1,"minecraft:crossbow":21,"minecraft:ender_pearl":1,"minecraft:shield":45,"minecraft:splash_potion":15,"minecraft:diamond_axe":100}},"DataVersion":3953}